a2y_inst/__init__.py
a2y_inst/ac_power_source.py
a2y_inst/asundar.py
a2y_inst/bg7tbl.py
a2y_inst/bluetooth.py
a2y_inst/curing.py
a2y_inst/dispenser.py
a2y_inst/dt1309.py
a2y_inst/gwinstek.py
a2y_inst/hspy.py
a2y_inst/itech.py
a2y_inst/jabil.py
a2y_inst/keyence.py
a2y_inst/kld.py
a2y_inst/lb1905.py
a2y_inst/mastech.py
a2y_inst/mind_vision.py
a2y_inst/mini_circuits.py
a2y_inst/mitsubishi.py
a2y_inst/mvs.py
a2y_inst/mvsdk.py
a2y_inst/ni845x.py
a2y_inst/rek.py
a2y_inst/shengpu.py
a2y_inst/tes.py
a2y_inst/victor.py
a2y_inst/wordop.py
a2y_inst/xinje.py
a2y_inst/yhd.py
a2y_inst/mvs_native/CameraParams_const.py
a2y_inst/mvs_native/CameraParams_header.py
a2y_inst/mvs_native/MvCameraControl_class.py
a2y_inst/mvs_native/MvErrorDefine_const.py
a2y_inst/mvs_native/MvISPErrorDefine_const.py
a2y_inst/mvs_native/PixelType_header.py
a2y_inst/mvs_native/__init__.py
a2y_inst-1.9.0.dist-info/LICENSE
a2y_inst-1.9.0.dist-info/METADATA
a2y_inst-1.9.0.dist-info/WHEEL
a2y_inst-1.9.0.dist-info/top_level.txt
a2y_inst-1.9.0.dist-info/RECORD
