Metadata-Version: 2.2
Name: a2y_inst
Version: 1.9.0
Summary: A module that contains kinds of instrument drivers.
Home-page: http://www.kersci.com/a2y/inst.html
Author: Yu Han
Author-email: hanjunyu@163.com
License: Private
Platform: Windows
Platform: Linux
Classifier: Development Status :: 4 - Beta
Classifier: Intended Audience :: Developers
Classifier: License :: Free For Educational Use
Classifier: Programming Language :: Python :: 3.6
Classifier: Operating System :: Microsoft :: Windows :: Windows 10
Classifier: Operating System :: POSIX :: Linux
License-File: LICENSE
Requires-Dist: pyserial>=3.4
Requires-Dist: a2y_handy
Requires-Dist: a2y_modbus>=2.1.1
Requires-Dist: bleak>=0.22.0
Dynamic: author
Dynamic: author-email
Dynamic: classifier
Dynamic: description
Dynamic: description-content-type
Dynamic: home-page
Dynamic: license
Dynamic: platform
Dynamic: requires-dist
Dynamic: summary
